simpledemotivators/Demotivator.py
simpledemotivators/Quote.py
simpledemotivators/__init__.py
simpledemotivators-2.1.0.dist-info/METADATA
simpledemotivators-2.1.0.dist-info/WHEEL
simpledemotivators-2.1.0.dist-info/top_level.txt
simpledemotivators-2.1.0.dist-info/RECORD
