Metadata-Version: 2.1
Name: simpledemotivators
Version: 2.1.0
Summary: Tool for easy demotivators
Home-page: https://github.com/Infqq/simpledemotivators
Author: infqq
Author-email: UNKNOWN
License: UNKNOWN
Platform: UNKNOWN
Classifier: Programming Language :: Python :: 3.6
Classifier: Programming Language :: Python :: 3.7
Classifier: Operating System :: OS Independent
Requires-Dist: pillow (==8.2.0)
Requires-Dist: requests (==2.25.1)
